webint_search/__init__.py
webint_search/templates/__init__.py
webint_search/templates/collections.html
webint_search/templates/index.html
webint_search/templates/opensearch.xml
webint_search/templates/results.html
webint_search/templates/youtube_results.html
webint_search-0.0.26.dist-info/METADATA
webint_search-0.0.26.dist-info/entry_points.txt
webint_search-0.0.26.dist-info/WHEEL
webint_search-0.0.26.dist-info/RECORD
