Metadata-Version: 2.1
Name: webint-search
Version: 0.0.26
Summary: search the web from your website
License: AGPL-3.0-or-later
Author: Angelo Gladding
Author-email: angelo@ragt.ag
Requires-Python: >=3.10,<3.11
Classifier: License :: OSI Approved :: GNU Affero General Public License v3 or later (AGPLv3+)
Classifier: Programming Language :: Python :: 3
Classifier: Programming Language :: Python :: 3.10
Requires-Dist: eng-to-ipa (>=0.0.2,<0.0.3)
Requires-Dist: nltk (>=3.8.1,<4.0.0)
Requires-Dist: pint (>=0.22,<0.23)
Requires-Dist: pronouncing (>=0.2.0,<0.3.0)
Requires-Dist: restrictedpython (>=6.2,<7.0)
Requires-Dist: typesense (>=0.18.0,<0.19.0)
Requires-Dist: webint (>=0.0)
Requires-Dist: webint-owner (>=0.0,<0.1)
Requires-Dist: wn (>=0.9.4,<0.10.0)
Requires-Dist: youtube-search (>=2.1.2,<3.0.0)
